pyreason/.cache_status.yaml
pyreason/__init__.py
pyreason/pyreason.py
pyreason/examples/hello-world/friends_graph.graphml
pyreason/scripts/__init__.py
pyreason/scripts/annotation_functions/__init__.py
pyreason/scripts/annotation_functions/annotation_functions.py
pyreason/scripts/components/__init__.py
pyreason/scripts/components/label.py
pyreason/scripts/components/world.py
pyreason/scripts/facts/__init__.py
pyreason/scripts/facts/fact.py
pyreason/scripts/facts/fact_edge.py
pyreason/scripts/facts/fact_node.py
pyreason/scripts/interpretation/__init__.py
pyreason/scripts/interpretation/interpretation.py
pyreason/scripts/interpretation/interpretation_dict.py
pyreason/scripts/interpretation/interpretation_fp.py
pyreason/scripts/interpretation/interpretation_parallel.py
pyreason/scripts/interval/__init__.py
pyreason/scripts/interval/interval.py
pyreason/scripts/learning/__init__.py
pyreason/scripts/learning/classification/__init__.py
pyreason/scripts/learning/classification/classifier.py
pyreason/scripts/learning/utils/__init__.py
pyreason/scripts/learning/utils/model_interface.py
pyreason/scripts/numba_wrapper/__init__.py
pyreason/scripts/numba_wrapper/numba_types/__init__.py
pyreason/scripts/numba_wrapper/numba_types/fact_edge_type.py
pyreason/scripts/numba_wrapper/numba_types/fact_node_type.py
pyreason/scripts/numba_wrapper/numba_types/interval_type.py
pyreason/scripts/numba_wrapper/numba_types/label_type.py
pyreason/scripts/numba_wrapper/numba_types/rule_type.py
pyreason/scripts/numba_wrapper/numba_types/world_type.py
pyreason/scripts/program/__init__.py
pyreason/scripts/program/program.py
pyreason/scripts/query/__init__.py
pyreason/scripts/query/query.py
pyreason/scripts/rules/__init__.py
pyreason/scripts/rules/rule.py
pyreason/scripts/rules/rule_internal.py
pyreason/scripts/threshold/__init__.py
pyreason/scripts/threshold/threshold.py
pyreason/scripts/utils/__init__.py
pyreason/scripts/utils/fact_parser.py
pyreason/scripts/utils/filter.py
pyreason-3.2.0.dist-info/licenses/LICENSE.md
pyreason-3.2.0.dist-info/METADATA
pyreason-3.2.0.dist-info/WHEEL
pyreason-3.2.0.dist-info/top_level.txt
pyreason-3.2.0.dist-info/RECORD
