Metadata-Version: 2.4
Name: pyreason
Version: 3.2.0
Summary: An explainable inference software supporting annotated, real valued, graph based and temporal logic
Home-page: https://github.com/lab-v2/pyreason
Author: Dyuman Aditya
Author-email: dyuman.aditya@gmail.com
License: BSD 3-clause
Project-URL: Bug Tracker, https://github.com/lab-v2/pyreason/issues
Project-URL: Repository, https://github.com/lab-v2/pyreason
Classifier: Programming Language :: Python :: 3
Classifier: License :: OSI Approved :: BSD License
Classifier: Operating System :: OS Independent
Requires-Python: >3.6
License-File: LICENSE.md
Requires-Dist: networkx
Requires-Dist: pyyaml
Requires-Dist: pandas
Requires-Dist: numba
Requires-Dist: numpy
Requires-Dist: memory_profiler
Requires-Dist: pytest
Dynamic: author
Dynamic: author-email
Dynamic: classifier
Dynamic: description
Dynamic: description-content-type
Dynamic: home-page
Dynamic: license
Dynamic: license-file
Dynamic: project-url
Dynamic: requires-dist
Dynamic: requires-python
Dynamic: summary
